interfax/__init__.py
interfax/account.py
interfax/client.py
interfax/documents.py
interfax/files.py
interfax/inbound.py
interfax/outbound.py
interfax/response.py
interfax-1.0.0.dist-info/DESCRIPTION.rst
interfax-1.0.0.dist-info/METADATA
interfax-1.0.0.dist-info/RECORD
interfax-1.0.0.dist-info/WHEEL
interfax-1.0.0.dist-info/metadata.json
interfax-1.0.0.dist-info/top_level.txt
