Metadata-Version: 2.0
Name: interfax
Version: 1.0.0
Summary: InterFAX python library
Home-page: http://github.com/interfax/interfax-python
Author: Daniel Knell
Author-email: contact@danielknell.co.uk
License: MIT
Platform: any
Classifier: Intended Audience :: Developers
Classifier: License :: OSI Approved :: MIT License
Classifier: Operating System :: OS Independent
Classifier: Programming Language :: Python
Classifier: Programming Language :: Python :: 2.7
Classifier: Programming Language :: Python :: 3
Classifier: Programming Language :: Python :: 3.3
Classifier: Programming Language :: Python :: 3.4
Classifier: Programming Language :: Python :: 3.5
Classifier: Topic :: Software Development :: Libraries :: Python Modules
Requires-Dist: cached-property (>=1.3.0)
Requires-Dist: inflection (>=0.3.1)
Requires-Dist: python-magic (>=0.4.12)
Requires-Dist: requests (>=2.11.1)
